spdx_tools/common/__init__.py
spdx_tools/common/spdx_licensing.py
spdx_tools/common/typing/__init__.py
spdx_tools/common/typing/constructor_type_errors.py
spdx_tools/common/typing/dataclass_with_properties.py
spdx_tools/common/typing/type_checks.py
spdx_tools/spdx/__init__.py
spdx_tools/spdx/casing_tools.py
spdx_tools/spdx/constants.py
spdx_tools/spdx/datetime_conversions.py
spdx_tools/spdx/document_utils.py
spdx_tools/spdx/formats.py
spdx_tools/spdx/graph_generation.py
spdx_tools/spdx/py.typed
spdx_tools/spdx/spdx_element_utils.py
spdx_tools/spdx/clitools/__init__.py
spdx_tools/spdx/clitools/pyspdxtools.py
spdx_tools/spdx/jsonschema/__init__.py
spdx_tools/spdx/jsonschema/annotation_converter.py
spdx_tools/spdx/jsonschema/annotation_properties.py
spdx_tools/spdx/jsonschema/checksum_converter.py
spdx_tools/spdx/jsonschema/checksum_properties.py
spdx_tools/spdx/jsonschema/converter.py
spdx_tools/spdx/jsonschema/creation_info_converter.py
spdx_tools/spdx/jsonschema/creation_info_properties.py
spdx_tools/spdx/jsonschema/document_converter.py
spdx_tools/spdx/jsonschema/document_properties.py
spdx_tools/spdx/jsonschema/external_document_ref_converter.py
spdx_tools/spdx/jsonschema/external_document_ref_properties.py
spdx_tools/spdx/jsonschema/external_package_ref_converter.py
spdx_tools/spdx/jsonschema/external_package_ref_properties.py
spdx_tools/spdx/jsonschema/extracted_licensing_info_converter.py
spdx_tools/spdx/jsonschema/extracted_licensing_info_properties.py
spdx_tools/spdx/jsonschema/file_converter.py
spdx_tools/spdx/jsonschema/file_properties.py
spdx_tools/spdx/jsonschema/json_property.py
spdx_tools/spdx/jsonschema/optional_utils.py
spdx_tools/spdx/jsonschema/package_converter.py
spdx_tools/spdx/jsonschema/package_properties.py
spdx_tools/spdx/jsonschema/package_verification_code_converter.py
spdx_tools/spdx/jsonschema/package_verification_code_properties.py
spdx_tools/spdx/jsonschema/relationship_converter.py
spdx_tools/spdx/jsonschema/relationship_properties.py
spdx_tools-0.8.2.dist-info/LICENSE
spdx_tools-0.8.2.dist-info/METADATA
spdx_tools-0.8.2.dist-info/WHEEL
spdx_tools-0.8.2.dist-info/entry_points.txt
spdx_tools-0.8.2.dist-info/top_level.txt
spdx_tools-0.8.2.dist-info/RECORD
