Metadata-Version: 2.1
Name: spdx-tools
Version: 0.8.2
Summary: SPDX parser and tools.
Author-email: "Ahmed H. Ismail" <ahm3d.hisham@gmail.com>
Maintainer: SPDX group at the Linux Foundation and others
Maintainer-email: Philippe Ombredanne <pombredanne@gmail.com>
License: Apache-2.0
Project-URL: Homepage, https://github.com/spdx/tools-python
Classifier: Intended Audience :: Developers
Classifier: Intended Audience :: System Administrators
Classifier: License :: OSI Approved :: Apache Software License
Classifier: Programming Language :: Python :: 3.7
Classifier: Programming Language :: Python :: 3.8
Classifier: Programming Language :: Python :: 3.9
Classifier: Programming Language :: Python :: 3.10
Classifier: Programming Language :: Python :: 3.11
Requires-Python: >=3.7
Provides-Extra: test
Provides-Extra: code_style
Provides-Extra: graph_generation
Provides-Extra: development
License-File: LICENSE
